[
  {
    "label": "FBlob",
    "kind": "Type",
    "detail": "struct declaration",
    "insertText": "FBlob"
  },
  {
    "label": "FBlobHandleData",
    "kind": "Type",
    "detail": "class declaration",
    "insertText": "FBlobHandleData"
  },
  {
    "label": "FBlobLocator",
    "kind": "Type",
    "detail": "class declaration",
    "insertText": "FBlobLocator"
  },
  {
    "label": "HORDE_API",
    "kind": "Type",
    "detail": "class declaration",
    "insertText": "HORDE_API"
  },
  {
    "label": "TBlobHandle",
    "kind": "Type",
    "detail": "class declaration",
    "insertText": "TBlobHandle"
  },
  {
    "label": "HORDE_API",
    "kind": "Type",
    "detail": "class declaration",
    "insertText": "HORDE_API"
  },
  {
    "label": "HORDE_API",
    "kind": "Type",
    "detail": "struct declaration",
    "insertText": "HORDE_API"
  },
  {
    "label": "GetTypeHash()",
    "kind": "Method",
    "detail": "Function (uint32)",
    "insertText": "GetTypeHash(const FBlobHandle& Handle)"
  }
]