[
  {
    "label": "_T1",
    "kind": "Type",
    "detail": "class declaration",
    "insertText": "_T1"
  },
  {
    "label": "_T2",
    "kind": "Type",
    "detail": "class declaration",
    "insertText": "_T2"
  },
  {
    "label": "__equal_to",
    "kind": "Type",
    "detail": "struct declaration",
    "insertText": "__equal_to"
  },
  {
    "label": "__less",
    "kind": "Type",
    "detail": "struct declaration",
    "insertText": "__less"
  },
  {
    "label": "defined()",
    "kind": "Method",
    "detail": "Function (# ifndef _LIBCPP___ALGORITHM_COMP_H # define _LIBCPP___ALGORITHM_COMP_H # include<__config> # if !)",
    "insertText": "defined(_LIBCPP_HAS_NO_PRAGMA_SYSTEM_HEADER)"
  },
  {
    "label": "operator()",
    "kind": "Method",
    "detail": "Function (_LIBCPP_INLINE_VISIBILITY _LIBCPP_CONSTEXPR_AFTER_CXX11 bool)",
    "insertText": "operator()(const _T1& __x, const _T1& __y)"
  }
]