[
  {
    "label": "FProperty",
    "kind": "Type",
    "detail": "class declaration",
    "insertText": "FProperty"
  },
  {
    "label": "FSpawnTabArgs",
    "kind": "Type",
    "detail": "class declaration",
    "insertText": "FSpawnTabArgs"
  },
  {
    "label": "SConfigEditor",
    "kind": "Type",
    "detail": "class declaration",
    "insertText": "SConfigEditor"
  },
  {
    "label": "SWidget",
    "kind": "Type",
    "detail": "class declaration",
    "insertText": "SWidget"
  },
  {
    "label": "FConfigEditorModule",
    "kind": "Type",
    "detail": "class declaration",
    "insertText": "FConfigEditorModule"
  },
  {
    "label": "SDockTab",
    "kind": "Type",
    "detail": "class declaration",
    "insertText": "SDockTab"
  },
  {
    "label": "StartupModule()",
    "kind": "Method",
    "detail": "Function (# pragma once # include \" Containers / Map . h \" # include \" Containers / UnrealString . h \" # include \" IConfigEditorModule . h \" # include \" Templates / SharedPointer . h \" # include \" UObject / WeakFieldPtr . h \" class FProperty ; class FSpawnTabArgs ; class SConfigEditor ; class SWidget ; class FConfigEditorModule : public IConfigEditorModule { public : void)",
    "insertText": "StartupModule()"
  },
  {
    "label": "ShutdownModule()",
    "kind": "Method",
    "detail": "Function (void)",
    "insertText": "ShutdownModule()"
  },
  {
    "label": "CreateHierarchyEditor()",
    "kind": "Method",
    "detail": "Function (public : void)",
    "insertText": "CreateHierarchyEditor(FProperty* EditProperty)"
  },
  {
    "label": "AddExternalPropertyValueWidgetAndConfigPairing()",
    "kind": "Method",
    "detail": "Function (void)",
    "insertText": "AddExternalPropertyValueWidgetAndConfigPairing(const FString& ConfigFile, const TSharedPtr<SWidget> ValueWidget)"
  },
  {
    "label": "GetValueWidgetForConfigProperty()",
    "kind": "Method",
    "detail": "Function (TSharedRef<SWidget>)",
    "insertText": "GetValueWidgetForConfigProperty(const FString& ConfigFile)"
  },
  {
    "label": "SpawnConfigEditorTab()",
    "kind": "Method",
    "detail": "Function (private : TSharedRef<class SDockTab>)",
    "insertText": "SpawnConfigEditorTab(const FSpawnTabArgs& Args)"
  }
]