[
  {
    "label": "FCustomTextFilterData",
    "kind": "Type",
    "detail": "struct declaration",
    "insertText": "FCustomTextFilterData"
  },
  {
    "label": "to",
    "kind": "Type",
    "detail": "class declaration",
    "insertText": "to"
  },
  {
    "label": "ICustomTextFilter",
    "kind": "Type",
    "detail": "class declaration",
    "insertText": "ICustomTextFilter"
  },
  {
    "label": "FCustomTextFilter",
    "kind": "Type",
    "detail": "class declaration",
    "insertText": "FCustomTextFilter"
  },
  {
    "label": "FName()",
    "kind": "Method",
    "detail": "Function (return)",
    "insertText": "FName(\"CustomTextFilter\")"
  }
]