[
  {
    "label": "FBXSDK_DLL",
    "kind": "Type",
    "detail": "class declaration",
    "insertText": "FBXSDK_DLL"
  },
  {
    "label": "EInterlaceMode",
    "kind": "Enum",
    "detail": "enum declaration",
    "insertText": "EInterlaceMode"
  },
  {
    "label": "FBXSDK_OBJECT_DECLARE()",
    "kind": "Method",
    "detail": "Function (# ifndef _FBXSDK_SCENE_VIDEO_H_ # define _FBXSDK_SCENE_VIDEO_H_ # include<fbxsdk / fbxsdk_def . h> # include<fbxsdk / scene / fbxmediaclip . h> # include<fbxsdk / fbxsdk_nsbegin . h> class FBXSDK_DLL FbxVideo : public FbxMediaClip {)",
    "insertText": "FBXSDK_OBJECT_DECLARE(FbxVideo, FbxMediaClip)"
  },
  {
    "label": "Reset()",
    "kind": "Method",
    "detail": "Function (public : void)",
    "insertText": "Reset()"
  },
  {
    "label": "ImageTextureSetMipMap()",
    "kind": "Method",
    "detail": "Function (void)",
    "insertText": "ImageTextureSetMipMap(bool pUseMipMap)"
  },
  {
    "label": "ImageTextureGetMipMap()",
    "kind": "Method",
    "detail": "Function (bool)",
    "insertText": "ImageTextureGetMipMap()"
  },
  {
    "label": "SetFileName()",
    "kind": "Method",
    "detail": "Function (bool)",
    "insertText": "SetFileName(const char* pName)"
  },
  {
    "label": "SetRelativeFileName()",
    "kind": "Method",
    "detail": "Function (bool)",
    "insertText": "SetRelativeFileName(const char* pName)"
  },
  {
    "label": "SetImageSequence()",
    "kind": "Method",
    "detail": "Function (void)",
    "insertText": "SetImageSequence(bool pImageSequence)"
  },
  {
    "label": "GetImageSequence()",
    "kind": "Method",
    "detail": "Function (bool)",
    "insertText": "GetImageSequence()"
  },
  {
    "label": "SetImageSequenceOffset()",
    "kind": "Method",
    "detail": "Function (void)",
    "insertText": "SetImageSequenceOffset(int pOffset)"
  },
  {
    "label": "GetImageSequenceOffset()",
    "kind": "Method",
    "detail": "Function (int)",
    "insertText": "GetImageSequenceOffset()"
  },
  {
    "label": "GetLastFrame()",
    "kind": "Method",
    "detail": "Function (int)",
    "insertText": "GetLastFrame()"
  },
  {
    "label": "GetWidth()",
    "kind": "Method",
    "detail": "Function (int)",
    "insertText": "GetWidth()"
  },
  {
    "label": "GetHeight()",
    "kind": "Method",
    "detail": "Function (int)",
    "insertText": "GetHeight()"
  },
  {
    "label": "SetStartFrame()",
    "kind": "Method",
    "detail": "Function (void)",
    "insertText": "SetStartFrame(int pStartFrame)"
  },
  {
    "label": "GetStartFrame()",
    "kind": "Method",
    "detail": "Function (int)",
    "insertText": "GetStartFrame()"
  },
  {
    "label": "SetStopFrame()",
    "kind": "Method",
    "detail": "Function (void)",
    "insertText": "SetStopFrame(int pStopFrame)"
  },
  {
    "label": "GetStopFrame()",
    "kind": "Method",
    "detail": "Function (int)",
    "insertText": "GetStopFrame()"
  },
  {
    "label": "SetInterlaceMode()",
    "kind": "Method",
    "detail": "Function (enum EInterlaceMode { eNone,eFields,eHalfEven,eHalfOdd,eFullEven,eFullOdd,eFullEvenOdd,eFullOddEven } ; void)",
    "insertText": "SetInterlaceMode(EInterlaceMode pInterlaceMode)"
  },
  {
    "label": "GetInterlaceMode()",
    "kind": "Method",
    "detail": "Function (EInterlaceMode)",
    "insertText": "GetInterlaceMode()"
  },
  {
    "label": "Construct()",
    "kind": "Method",
    "detail": "Function (# ifndef DOXYGEN_SHOULD_SKIP_THIS protected : void)",
    "insertText": "Construct(const FbxObject* pFrom)"
  },
  {
    "label": "ConstructProperties()",
    "kind": "Method",
    "detail": "Function (void)",
    "insertText": "ConstructProperties(bool pForceSet)"
  },
  {
    "label": "ConnectNotify()",
    "kind": "Method",
    "detail": "Function (bool)",
    "insertText": "ConnectNotify(FbxConnectEvent const &pEvent)"
  },
  {
    "label": "Copy()",
    "kind": "Method",
    "detail": "Function (public : FbxObject&)",
    "insertText": "Copy(const FbxObject& pObject)"
  },
  {
    "label": "Init()",
    "kind": "Method",
    "detail": "Function (FbxPropertyT<FbxBool> ImageSequence ; FbxPropertyT<FbxInt> ImageSequenceOffset ; FbxPropertyT<FbxDouble> FrameRate ; FbxPropertyT<FbxInt> LastFrame ; FbxPropertyT<FbxInt> Width ; FbxPropertyT<FbxInt> Height ; FbxPropertyT<FbxInt> StartFrame ; FbxPropertyT<FbxInt> StopFrame ; FbxPropertyT<EInterlaceMode> InterlaceMode ; protected : void)",
    "insertText": "Init()"
  },
  {
    "label": "FbxTypeOf()",
    "kind": "Method",
    "detail": "Function (bool mUseMipMap ; # endif } ; EFbxType)",
    "insertText": "FbxTypeOf(const FbxVideo::EInterlaceMode&)"
  }
]