[
  {
    "label": "FBlueprintActionDatabaseRegistrar",
    "kind": "Type",
    "detail": "class declaration",
    "insertText": "FBlueprintActionDatabaseRegistrar"
  },
  {
    "label": "UEdGraphPin",
    "kind": "Type",
    "detail": "class declaration",
    "insertText": "UEdGraphPin"
  },
  {
    "label": "UObject",
    "kind": "Type",
    "detail": "class declaration",
    "insertText": "UObject"
  },
  {
    "label": "FLinearColor",
    "kind": "Type",
    "detail": "struct declaration",
    "insertText": "FLinearColor"
  },
  {
    "label": "UK2Node_MakeSet",
    "kind": "Type",
    "detail": "class declaration",
    "insertText": "UK2Node_MakeSet"
  },
  {
    "label": "FCompilerResultsLog",
    "kind": "Type",
    "detail": "class declaration",
    "insertText": "FCompilerResultsLog"
  },
  {
    "label": "UToolMenu",
    "kind": "Type",
    "detail": "class declaration",
    "insertText": "UToolMenu"
  },
  {
    "label": "UGraphNodeContextMenuContext",
    "kind": "Type",
    "detail": "class declaration",
    "insertText": "UGraphNodeContextMenuContext"
  },
  {
    "label": "FNodeHandlingFunctor",
    "kind": "Type",
    "detail": "class declaration",
    "insertText": "FNodeHandlingFunctor"
  },
  {
    "label": "FKismetCompilerContext",
    "kind": "Type",
    "detail": "class declaration",
    "insertText": "FKismetCompilerContext"
  },
  {
    "label": "UCLASS()",
    "kind": "Method",
    "detail": "Function (# pragma once # include \" EdGraph / EdGraphNode . h \" # include \" Internationalization / Text . h \" # include \" K2Node_MakeContainer . h \" # include \" Textures / SlateIcon . h \" # include \" UObject / NameTypes . h \" # include \" UObject / ObjectMacros . h \" # include \" UObject / UObjectGlobals . h \" # include \" K2Node_MakeSet . generated . h \" class FBlueprintActionDatabaseRegistrar ; class UEdGraphPin ; class UObject ; struct FLinearColor ;)",
    "insertText": "UCLASS(MinimalAPI)"
  },
  {
    "label": "GENERATED_UCLASS_BODY()",
    "kind": "Method",
    "detail": "Function (void)",
    "insertText": "GENERATED_UCLASS_BODY() public: virtual FText GetNodeTitle(ENodeTitleType::Type TitleType)"
  },
  {
    "label": "GetTooltipText()",
    "kind": "Method",
    "detail": "Function (FText)",
    "insertText": "GetTooltipText()"
  },
  {
    "label": "GetIconAndTint()",
    "kind": "Method",
    "detail": "Function (FSlateIcon)",
    "insertText": "GetIconAndTint(FLinearColor& OutColor)"
  },
  {
    "label": "ValidateNodeDuringCompilation()",
    "kind": "Method",
    "detail": "Function (void)",
    "insertText": "ValidateNodeDuringCompilation(class FCompilerResultsLog& MessageLog)"
  },
  {
    "label": "GetNodeContextMenuActions()",
    "kind": "Method",
    "detail": "Function (void)",
    "insertText": "GetNodeContextMenuActions(class UToolMenu* Menu, class UGraphNodeContextMenuContext* Context)"
  },
  {
    "label": "IncludeParentNodeContextMenu()",
    "kind": "Method",
    "detail": "Function (bool)",
    "insertText": "IncludeParentNodeContextMenu()"
  },
  {
    "label": "GetMenuCategory()",
    "kind": "Method",
    "detail": "Function (FText)",
    "insertText": "GetMenuCategory()"
  },
  {
    "label": "GetOutputPinName()",
    "kind": "Method",
    "detail": "Function (FName)",
    "insertText": "GetOutputPinName()"
  }
]