[
  {
    "label": "FRDGBuilder",
    "kind": "Type",
    "detail": "class declaration",
    "insertText": "FRDGBuilder"
  },
  {
    "label": "FViewInfo",
    "kind": "Type",
    "detail": "class declaration",
    "insertText": "FViewInfo"
  },
  {
    "label": "FCompositePrimitiveInputs",
    "kind": "Type",
    "detail": "struct declaration",
    "insertText": "FCompositePrimitiveInputs"
  },
  {
    "label": "FScreenPassRenderTarget",
    "kind": "Type",
    "detail": "struct declaration",
    "insertText": "FScreenPassRenderTarget"
  },
  {
    "label": "ComposeMeshEdges()",
    "kind": "Method",
    "detail": "Function (# pragma once # include \" MeshEdges . h \" class FRDGBuilder ; class FViewInfo ; struct FCompositePrimitiveInputs ; struct FScreenPassRenderTarget ; void)",
    "insertText": "ComposeMeshEdges(FRDGBuilder& GraphBuilder, const FViewInfo& View, FScreenPassRenderTarget& EditorPrimitivesColor, FScreenPassRenderTarget& EditorPrimitivesDepth)"
  }
]