[
  {
    "label": "FMovieSceneSequenceLoopCount",
    "kind": "Type",
    "detail": "struct declaration",
    "insertText": "FMovieSceneSequenceLoopCount"
  },
  {
    "label": "TStructOpsTypeTraits",
    "kind": "Type",
    "detail": "struct declaration",
    "insertText": "TStructOpsTypeTraits"
  },
  {
    "label": "class",
    "kind": "Enum",
    "detail": "enum declaration",
    "insertText": "class"
  },
  {
    "label": "FMovieSceneSequencePlaybackSettings",
    "kind": "Type",
    "detail": "struct declaration",
    "insertText": "FMovieSceneSequencePlaybackSettings"
  },
  {
    "label": "USTRUCT()",
    "kind": "Method",
    "detail": "Function (# pragma once # include \" CoreTypes . h \" # include \" UObject / ObjectMacros . h \" # include \" MovieSceneSequenceTickInterval . h \" # include \" MovieSceneSequencePlaybackSettings . generated . h \")",
    "insertText": "USTRUCT(BlueprintType)"
  },
  {
    "label": "FMovieSceneSequenceLoopCount()",
    "kind": "Method",
    "detail": "Function (void)",
    "insertText": "FMovieSceneSequenceLoopCount() : Value(0)"
  },
  {
    "label": "GENERATED_BODY()",
    "kind": "Method",
    "detail": "Function (})",
    "insertText": "GENERATED_BODY() bool SerializeFromMismatchedTag(const FPropertyTag& Tag, FStructuredArchive::FSlot Slot)"
  },
  {
    "label": "UENUM()",
    "kind": "Method",
    "detail": "Function (} ; template<> struct TStructOpsTypeTraits<FMovieSceneSequenceLoopCount> : public TStructOpsTypeTraitsBase2<FMovieSceneSequenceLoopCount> { enum { WithStructuredSerializeFromMismatchedTag = true } ; } ;)",
    "insertText": "UENUM(BlueprintType)"
  },
  {
    "label": "UMETA()",
    "kind": "Method",
    "detail": "Function (None)",
    "insertText": "UMETA(DisplayName = \"None\"), ForceKeepState UMETA(DisplayName=\"Force Keep State\"), ForceRestoreState UMETA(DisplayName=\"Force Restore State\")"
  },
  {
    "label": "FMovieSceneSequencePlaybackSettings()",
    "kind": "Method",
    "detail": "Function (void)",
    "insertText": "FMovieSceneSequencePlaybackSettings() : bAutoPlay(false) , PlayRate(1.f) , StartTime(0.f) , bRandomStartTime(false) #if WITH_EDITORONLY_DATA , bRestoreState_DEPRECATED(false) #endif , bDisableMovementInput(false) , bDisableLookAtInput(false) , bHidePlayer(false) , bHideHud(false) , bDisableCameraCuts(false) , bPauseAtEnd(false) , bInheritTickIntervalFromOwner(true) , bDynamicWeighting(false)"
  },
  {
    "label": "GENERATED_BODY()",
    "kind": "Method",
    "detail": "Function (})",
    "insertText": "GENERATED_BODY() UPROPERTY(EditAnywhere, BlueprintReadWrite, Category = \"Playback\")"
  },
  {
    "label": "SerializeFromMismatchedTag()",
    "kind": "Method",
    "detail": "Function (bool)",
    "insertText": "SerializeFromMismatchedTag(const FPropertyTag& Tag, FStructuredArchive::FSlot Slot)"
  }
]