[
  {
    "label": "AController",
    "kind": "Type",
    "detail": "class declaration",
    "insertText": "AController"
  },
  {
    "label": "UPathFollowingManager",
    "kind": "Type",
    "detail": "class declaration",
    "insertText": "UPathFollowingManager"
  },
  {
    "label": "StopMovement()",
    "kind": "Method",
    "detail": "Function (void)",
    "insertText": "StopMovement(const AController& Controller)"
  },
  {
    "label": "IsFollowingAPath()",
    "kind": "Method",
    "detail": "Function (bool)",
    "insertText": "IsFollowingAPath(const AController& Controller)"
  }
]