[
  {
    "label": "FMaterialHandle",
    "kind": "Type",
    "detail": "struct declaration",
    "insertText": "FMaterialHandle"
  },
  {
    "label": "FConstMaterialHandle",
    "kind": "Type",
    "detail": "struct declaration",
    "insertText": "FConstMaterialHandle"
  },
  {
    "label": "FMaterialMaskHandle",
    "kind": "Type",
    "detail": "struct declaration",
    "insertText": "FMaterialMaskHandle"
  },
  {
    "label": "FConstMaterialMaskHandle",
    "kind": "Type",
    "detail": "struct declaration",
    "insertText": "FConstMaterialMaskHandle"
  },
  {
    "label": "FPhysicalMaterialManager",
    "kind": "Type",
    "detail": "class declaration",
    "insertText": "FPhysicalMaterialManager"
  },
  {
    "label": "Get()",
    "kind": "Method",
    "detail": "Function (# pragma once # include \" Chaos / Core . h \" # include \" Chaos / Defines . h \" # include \" Chaos / Framework / Handles . h \" namespace Chaos { using FMaterialArray = THandleArray<FChaosPhysicsMaterial> ; using FChaosMaterialHandle = FMaterialArray::FHandle ; using FChaosConstMaterialHandle = FMaterialArray::FConstHandle ; using FMaterialMaskArray = THandleArray<FChaosPhysicsMaterialMask> ; using FChaosMaterialMaskHandle = FMaterialMaskArray::FHandle ; using FChaosConstMaterialMaskHandle = FMaterialMaskArray::FConstHandle ; struct FMaterialHandle { FChaosPhysicsMaterial*)",
    "insertText": "Get()"
  },
  {
    "label": "GetInternal()",
    "kind": "Method",
    "detail": "Function (FChaosPhysicsMaterial*)",
    "insertText": "GetInternal(const THandleArray<FChaosPhysicsMaterial>* const SimMaterials)"
  },
  {
    "label": "IsValid()",
    "kind": "Method",
    "detail": "Function (FChaosMaterialHandle InnerHandle ; bool)",
    "insertText": "IsValid()"
  },
  {
    "label": "IsValidInternal()",
    "kind": "Method",
    "detail": "Function (} bool)",
    "insertText": "IsValidInternal(const THandleArray<FChaosPhysicsMaterial>* const SimMaterials)"
  },
  {
    "label": "Reset()",
    "kind": "Method",
    "detail": "Function (} void)",
    "insertText": "Reset()"
  },
  {
    "label": "FChaosMaterialHandle()",
    "kind": "Method",
    "detail": "Function (InnerHandle =)",
    "insertText": "FChaosMaterialHandle()"
  },
  {
    "label": "operator()",
    "kind": "Method",
    "detail": "Function (} bool)",
    "insertText": "operator(const FMaterialHandle& A, const FMaterialHandle& B)"
  },
  {
    "label": "operator()",
    "kind": "Method",
    "detail": "Function (} bool)",
    "insertText": "operator(const FConstMaterialHandle& A, const FConstMaterialHandle& B)"
  },
  {
    "label": "operator()",
    "kind": "Method",
    "detail": "Function (} bool)",
    "insertText": "operator(const FMaterialMaskHandle& A, const FMaterialMaskHandle& B)"
  },
  {
    "label": "operator()",
    "kind": "Method",
    "detail": "Function (} bool)",
    "insertText": "operator(const FConstMaterialMaskHandle& A, const FConstMaterialMaskHandle& B)"
  },
  {
    "label": "DECLARE_MULTICAST_DELEGATE_OneParam()",
    "kind": "Method",
    "detail": "Function (Ar<<Value . InnerHandle ; return Ar ; } } ;)",
    "insertText": "DECLARE_MULTICAST_DELEGATE_OneParam(FOnMaterialCreated, FMaterialHandle)"
  },
  {
    "label": "DECLARE_MULTICAST_DELEGATE_OneParam()",
    "kind": "Method",
    "detail": "Function (void)",
    "insertText": "DECLARE_MULTICAST_DELEGATE_OneParam(FOnMaterialDestroyed, FMaterialHandle)"
  },
  {
    "label": "DECLARE_MULTICAST_DELEGATE_OneParam()",
    "kind": "Method",
    "detail": "Function (void)",
    "insertText": "DECLARE_MULTICAST_DELEGATE_OneParam(FOnMaterialUpdated, FMaterialHandle)"
  },
  {
    "label": "DECLARE_MULTICAST_DELEGATE_OneParam()",
    "kind": "Method",
    "detail": "Function (void)",
    "insertText": "DECLARE_MULTICAST_DELEGATE_OneParam(FOnMaterialMaskCreated, FMaterialMaskHandle)"
  },
  {
    "label": "DECLARE_MULTICAST_DELEGATE_OneParam()",
    "kind": "Method",
    "detail": "Function (void)",
    "insertText": "DECLARE_MULTICAST_DELEGATE_OneParam(FOnMaterialMaskDestroyed, FMaterialMaskHandle)"
  },
  {
    "label": "DECLARE_MULTICAST_DELEGATE_OneParam()",
    "kind": "Method",
    "detail": "Function (void)",
    "insertText": "DECLARE_MULTICAST_DELEGATE_OneParam(FOnMaterialMaskUpdated, FMaterialMaskHandle)"
  },
  {
    "label": "Create()",
    "kind": "Method",
    "detail": "Function (FMaterialHandle)",
    "insertText": "Create()"
  },
  {
    "label": "CreateMask()",
    "kind": "Method",
    "detail": "Function (FMaterialMaskHandle)",
    "insertText": "CreateMask()"
  },
  {
    "label": "Destroy()",
    "kind": "Method",
    "detail": "Function (void)",
    "insertText": "Destroy(FMaterialHandle InHandle)"
  },
  {
    "label": "Destroy()",
    "kind": "Method",
    "detail": "Function (void)",
    "insertText": "Destroy(FMaterialMaskHandle InHandle)"
  },
  {
    "label": "Resolve()",
    "kind": "Method",
    "detail": "Function (FChaosPhysicsMaterial*)",
    "insertText": "Resolve(FChaosMaterialHandle InHandle)"
  },
  {
    "label": "Resolve()",
    "kind": "Method",
    "detail": "Function (const FChaosPhysicsMaterial*)",
    "insertText": "Resolve(FChaosConstMaterialHandle InHandle)"
  },
  {
    "label": "Resolve()",
    "kind": "Method",
    "detail": "Function (FChaosPhysicsMaterialMask*)",
    "insertText": "Resolve(FChaosMaterialMaskHandle InHandle)"
  },
  {
    "label": "Resolve()",
    "kind": "Method",
    "detail": "Function (const FChaosPhysicsMaterialMask*)",
    "insertText": "Resolve(FChaosConstMaterialMaskHandle InHandle)"
  },
  {
    "label": "UpdateMaterial()",
    "kind": "Method",
    "detail": "Function (void)",
    "insertText": "UpdateMaterial(FMaterialHandle InHandle)"
  },
  {
    "label": "UpdateMaterialMask()",
    "kind": "Method",
    "detail": "Function (void)",
    "insertText": "UpdateMaterialMask(FMaterialMaskHandle InHandle)"
  },
  {
    "label": "GetPrimaryMaterials_External()",
    "kind": "Method",
    "detail": "Function (const THandleArray<FChaosPhysicsMaterial>&)",
    "insertText": "GetPrimaryMaterials_External()"
  },
  {
    "label": "GetPrimaryMaterialMasks_External()",
    "kind": "Method",
    "detail": "Function (const THandleArray<FChaosPhysicsMaterialMask>&)",
    "insertText": "GetPrimaryMaterialMasks_External()"
  },
  {
    "label": "FPhysicalMaterialManager()",
    "kind": "Method",
    "detail": "Function (FOnMaterialUpdated OnMaterialUpdated ; FOnMaterialCreated OnMaterialCreated ; FOnMaterialDestroyed OnMaterialDestroyed ; FOnMaterialMaskUpdated OnMaterialMaskUpdated ; FOnMaterialMaskCreated OnMaterialMaskCreated ; FOnMaterialMaskDestroyed OnMaterialMaskDestroyed ; private : int32 InitialCapacity = 4 ;)",
    "insertText": "FPhysicalMaterialManager()"
  }
]