[
  {
    "label": "FPoseWatchManagerDefaultMode",
    "kind": "Type",
    "detail": "class declaration",
    "insertText": "FPoseWatchManagerDefaultMode"
  },
  {
    "label": "FPoseWatchManagerDefaultHierarchy",
    "kind": "Type",
    "detail": "class declaration",
    "insertText": "FPoseWatchManagerDefaultHierarchy"
  },
  {
    "label": "FPoseWatchManagerDefaultHierarchy()",
    "kind": "Method",
    "detail": "Function (# pragma once # include \" CoreMinimal . h \" # include \" PoseWatchManagerFwd . h \" # include \" IPoseWatchManagerTreeItem . h \" class FPoseWatchManagerDefaultMode ; class FPoseWatchManagerDefaultHierarchy { public :)",
    "insertText": "FPoseWatchManagerDefaultHierarchy(FPoseWatchManagerDefaultMode* InMode)"
  },
  {
    "label": "FindParent()",
    "kind": "Method",
    "detail": "Function (FPoseWatchManagerTreeItemPtr)",
    "insertText": "FindParent(const IPoseWatchManagerTreeItem& Item, const TMap<FObjectKey, FPoseWatchManagerTreeItemPtr>& Items)"
  },
  {
    "label": "CreateItems()",
    "kind": "Method",
    "detail": "Function (void)",
    "insertText": "CreateItems(TArray<FPoseWatchManagerTreeItemPtr>& OutItems)"
  }
]