[
  {
    "label": "FName",
    "kind": "Type",
    "detail": "class declaration",
    "insertText": "FName"
  },
  {
    "label": "IOutlinerExtension",
    "kind": "Type",
    "detail": "class declaration",
    "insertText": "IOutlinerExtension"
  },
  {
    "label": "ITrackExtension",
    "kind": "Type",
    "detail": "class declaration",
    "insertText": "ITrackExtension"
  },
  {
    "label": "GetParentTrackNodeAndNamePath()",
    "kind": "Method",
    "detail": "Function (TViewModelPtr<ITrackExtension>)",
    "insertText": "GetParentTrackNodeAndNamePath(const TViewModelPtr<IOutlinerExtension>& Node, TArray<FName>& OutNamePath)"
  }
]