[
  {
    "label": "SBox",
    "kind": "Type",
    "detail": "class declaration",
    "insertText": "SBox"
  },
  {
    "label": "USizeBox",
    "kind": "Type",
    "detail": "class declaration",
    "insertText": "USizeBox"
  },
  {
    "label": "SetWidthOverride()",
    "kind": "Method",
    "detail": "Function (void)",
    "insertText": "SetWidthOverride(float InWidthOverride)"
  },
  {
    "label": "ClearWidthOverride()",
    "kind": "Method",
    "detail": "Function (void)",
    "insertText": "ClearWidthOverride()"
  },
  {
    "label": "SetHeightOverride()",
    "kind": "Method",
    "detail": "Function (void)",
    "insertText": "SetHeightOverride(float InHeightOverride)"
  },
  {
    "label": "ClearHeightOverride()",
    "kind": "Method",
    "detail": "Function (void)",
    "insertText": "ClearHeightOverride()"
  },
  {
    "label": "SetMinDesiredWidth()",
    "kind": "Method",
    "detail": "Function (void)",
    "insertText": "SetMinDesiredWidth(float InMinDesiredWidth)"
  },
  {
    "label": "ClearMinDesiredWidth()",
    "kind": "Method",
    "detail": "Function (void)",
    "insertText": "ClearMinDesiredWidth()"
  },
  {
    "label": "SetMinDesiredHeight()",
    "kind": "Method",
    "detail": "Function (void)",
    "insertText": "SetMinDesiredHeight(float InMinDesiredHeight)"
  },
  {
    "label": "ClearMinDesiredHeight()",
    "kind": "Method",
    "detail": "Function (void)",
    "insertText": "ClearMinDesiredHeight()"
  },
  {
    "label": "SetMaxDesiredWidth()",
    "kind": "Method",
    "detail": "Function (void)",
    "insertText": "SetMaxDesiredWidth(float InMaxDesiredWidth)"
  },
  {
    "label": "ClearMaxDesiredWidth()",
    "kind": "Method",
    "detail": "Function (void)",
    "insertText": "ClearMaxDesiredWidth()"
  },
  {
    "label": "SetMaxDesiredHeight()",
    "kind": "Method",
    "detail": "Function (void)",
    "insertText": "SetMaxDesiredHeight(float InMaxDesiredHeight)"
  },
  {
    "label": "ClearMaxDesiredHeight()",
    "kind": "Method",
    "detail": "Function (void)",
    "insertText": "ClearMaxDesiredHeight()"
  },
  {
    "label": "SetMinAspectRatio()",
    "kind": "Method",
    "detail": "Function (void)",
    "insertText": "SetMinAspectRatio(float InMinAspectRatio)"
  },
  {
    "label": "ClearMinAspectRatio()",
    "kind": "Method",
    "detail": "Function (void)",
    "insertText": "ClearMinAspectRatio()"
  },
  {
    "label": "SetMaxAspectRatio()",
    "kind": "Method",
    "detail": "Function (void)",
    "insertText": "SetMaxAspectRatio(float InMaxAspectRatio)"
  },
  {
    "label": "ClearMaxAspectRatio()",
    "kind": "Method",
    "detail": "Function (void)",
    "insertText": "ClearMaxAspectRatio()"
  }
]