[
  {
    "label": "USourceCodeAccessSettings",
    "kind": "Type",
    "detail": "class declaration",
    "insertText": "USourceCodeAccessSettings"
  },
  {
    "label": "UCLASS()",
    "kind": "Method",
    "detail": "Function (# pragma once # include \" CoreMinimal . h \" # include \" UObject / ObjectMacros . h \" # include \" UObject / Object . h \" # include \" SourceCodeAccessSettings . generated . h \")",
    "insertText": "UCLASS(config=EditorSettings)"
  },
  {
    "label": "GENERATED_UCLASS_BODY()",
    "kind": "Method",
    "detail": "Function (void)",
    "insertText": "GENERATED_UCLASS_BODY() UPROPERTY(Config, EditAnywhere, Category=\"Source Code Editor\", meta=(DisplayName=\"Source Code Editor\", ConfigRestartRequired = true))"
  }
]