[
  {
    "label": "UTextPropertyTestObject",
    "kind": "Type",
    "detail": "class declaration",
    "insertText": "UTextPropertyTestObject"
  },
  {
    "label": "UCLASS()",
    "kind": "Method",
    "detail": "Function (# pragma once # include \" CoreMinimal . h \" # include \" UObject / ObjectMacros . h \" # include \" UObject / Object . h \" # include \" TextPropertyTestObject . generated . h \")",
    "insertText": "UCLASS()"
  },
  {
    "label": "GENERATED_UCLASS_BODY()",
    "kind": "Method",
    "detail": "Function (void)",
    "insertText": "GENERATED_UCLASS_BODY() public: UPROPERTY()"
  }
]