[
  {
    "label": "GenerateIndexHash()",
    "kind": "Method",
    "detail": "Function (# pragma once # include \" Containers / StringFwd . h \" # include \" Containers / UnrealString . h \" # include \" Elements / Interfaces / TypedElementQueryStorageInterfaces . h \" # include \" UObject / NameTypes . h \" # include \" UObject / ObjectPtr . h \" # include \" UObject / SoftObjectPath . h \" # include \" UObject / StrongObjectPtr . h \" # include \" UObject / WeakObjectPtrTemplates . h \" namespace UE::Editor::DataStorage { template<T> IndexHash)",
    "insertText": "GenerateIndexHash(const T* Object)"
  },
  {
    "label": "GenerateIndexHash()",
    "kind": "Method",
    "detail": "Function (template<T> IndexHash)",
    "insertText": "GenerateIndexHash(const TWeakObjectPtr<T>& Object)"
  },
  {
    "label": "GenerateIndexHash()",
    "kind": "Method",
    "detail": "Function (template<T> IndexHash)",
    "insertText": "GenerateIndexHash(const TObjectPtr<T>& Object)"
  },
  {
    "label": "GenerateIndexHash()",
    "kind": "Method",
    "detail": "Function (template<T> IndexHash)",
    "insertText": "GenerateIndexHash(const TStrongObjectPtr<T>& Object)"
  },
  {
    "label": "GenerateIndexHash()",
    "kind": "Method",
    "detail": "Function (IndexHash)",
    "insertText": "GenerateIndexHash(const FString& Object)"
  },
  {
    "label": "GenerateIndexHash()",
    "kind": "Method",
    "detail": "Function (IndexHash)",
    "insertText": "GenerateIndexHash(FStringView Object)"
  },
  {
    "label": "GenerateIndexHash()",
    "kind": "Method",
    "detail": "Function (IndexHash)",
    "insertText": "GenerateIndexHash(FName Object)"
  },
  {
    "label": "GenerateIndexHash()",
    "kind": "Method",
    "detail": "Function (IndexHash)",
    "insertText": "GenerateIndexHash(const FSoftObjectPath& ObjectPath)"
  }
]