[
  {
    "label": "UBiDiTransform",
    "kind": "Type",
    "detail": "struct declaration",
    "insertText": "UBiDiTransform"
  },
  {
    "label": "ubiditransform_transform()",
    "kind": "Method",
    "detail": "Function (# ifndef UBIDITRANSFORM_H # define UBIDITRANSFORM_H # include \" unicode / utypes . h \" # include \" unicode / ubidi . h \" # include \" unicode / uchar . h \" # include \" unicode / localpointer . h \" typedef enum { UBIDI_LOGICAL = 0,UBIDI_VISUAL } UBiDiOrder ; typedef enum { UBIDI_MIRRORING_OFF = 0,UBIDI_MIRRORING_ON } UBiDiMirroring ; typedef struct UBiDiTransform UBiDiTransform ; U_STABLE uint32_t U_EXPORT2)",
    "insertText": "ubiditransform_transform(UBiDiTransform *pBiDiTransform, const UChar *src, int32_t srcLength, UChar *dest, int32_t destSize, UBiDiLevel inParaLevel, UBiDiOrder inOrder, UBiDiLevel outParaLevel, UBiDiOrder outOrder, UBiDiMirroring doMirroring, uint32_t shapingOptions, UErrorCode *pErrorCode)"
  },
  {
    "label": "ubiditransform_open()",
    "kind": "Method",
    "detail": "Function (U_STABLE UBiDiTransform* U_EXPORT2)",
    "insertText": "ubiditransform_open(UErrorCode *pErrorCode)"
  },
  {
    "label": "ubiditransform_close()",
    "kind": "Method",
    "detail": "Function (U_STABLE void U_EXPORT2)",
    "insertText": "ubiditransform_close(UBiDiTransform *pBidiTransform)"
  },
  {
    "label": "U_DEFINE_LOCAL_OPEN_POINTER()",
    "kind": "Method",
    "detail": "Function (# if U_NAMESPACE_BEGIN)",
    "insertText": "U_DEFINE_LOCAL_OPEN_POINTER(LocalUBiDiTransformPointer, UBiDiTransform, ubiditransform_close)"
  }
]