[
  {
    "label": "U_COMMON_API",
    "kind": "Type",
    "detail": "class declaration",
    "insertText": "U_COMMON_API"
  },
  {
    "label": "U_ETHER()",
    "kind": "Method",
    "detail": "Function (# ifndef UNIFILT_H # define UNIFILT_H # include \" unicode / unifunct . h \" # include \" unicode / unimatch . h \" U_NAMESPACE_BEGIN # define)",
    "insertText": "U_ETHER((char16_t)0xFFFF)"
  },
  {
    "label": "UnicodeFilter()",
    "kind": "Method",
    "detail": "Function (public : ~)",
    "insertText": "UnicodeFilter()"
  },
  {
    "label": "contains()",
    "kind": "Method",
    "detail": "Function (UBool)",
    "insertText": "contains(UChar32 c)"
  },
  {
    "label": "toMatcher()",
    "kind": "Method",
    "detail": "Function (UnicodeMatcher*)",
    "insertText": "toMatcher()"
  },
  {
    "label": "matches()",
    "kind": "Method",
    "detail": "Function (UMatchDegree)",
    "insertText": "matches(const Replaceable& text, int32_t& offset, int32_t limit, UBool incremental)"
  },
  {
    "label": "setData()",
    "kind": "Method",
    "detail": "Function (void)",
    "insertText": "setData(const TransliterationRuleData*)"
  },
  {
    "label": "getStaticClassID()",
    "kind": "Method",
    "detail": "Function (UClassID U_EXPORT2)",
    "insertText": "getStaticClassID()"
  }
]